{"assignees":[],"author":{"id":"MDQ6VXNlcjExOTQyMg==","is_bot":false,"login":"tsurdilo","name":"Tihomir Surdilovic"},"body":"RetryState.RETRY_STATE_IN_PROGRESS\r\nis used internally only but is exposed via public api: https://github.com/temporalio/api/blob/master/temporal/api/enums/v1/workflow.proto#L107\r\n\r\nThis is causing some confusions to our users. If possible please remove it (keep it internal only). \r\n\r\nIdk if this should be issue opened on the server or here. Please let me know if this repo is wrong place for it.","closedAt":null,"comments":[],"createdAt":"2022-09-01T05:50:39Z","labels":[{"id":"MDU6TGFiZWwxNjQzNjQ3OTQ1","name":"enhancement","description":"New feature or request","color":"a2eeef"}],"milestone":null,"number":232,"reactionGroups":[],"state":"OPEN","title":"[Feature Request] Remove RetryState.RETRY_STATE_IN_PROGRESS from public api","updatedAt":"2022-09-01T05:50:39Z","url":"https://github.com/temporalio/api/issues/232"}
