{
  "summary": "Feature request to add plugin support to the .NET SDK, as part of the broader Temporal plugin architecture initiative referenced in the features repository.",
  "category": "feature",
  "subcategory": "plugin-system",
  "apis": [],
  "components": [
    "sdk-core",
    "extension-system"
  ],
  "concepts": [
    "extensibility",
    "plugin-architecture",
    "modularity",
    "integration-points",
    "custom-extensions"
  ],
  "severity": "medium",
  "userImpact": "Users would be able to extend SDK functionality through a plugin mechanism, enabling custom integrations and behavior.",
  "rootCause": null,
  "proposedFix": null,
  "workaround": null,
  "resolution": "fixed",
  "resolutionDetails": "Plugin support was implemented as part of the broader SDK extension architecture",
  "related": [
    652
  ],
  "keyQuote": "See https://github.com/temporalio/features/issues/652",
  "number": 507,
  "repo": "temporalio-sdk-dotnet",
  "generatedAt": "2026-01-11T15:31:08.896Z"
}