{
  "summary": "Request to add a Summary field to LocalActivityOptions for better tracking and identification of local activities in the .NET SDK.",
  "category": "feature",
  "subcategory": "local-activities",
  "apis": [
    "LocalActivityOptions"
  ],
  "components": [
    "local-activity-executor",
    "options-builder"
  ],
  "concepts": [
    "local-activity",
    "summary",
    "metadata",
    "activity-tracking"
  ],
  "severity": "low",
  "userImpact": "Users would have better visibility and control over local activity metadata in the .NET SDK.",
  "rootCause": null,
  "proposedFix": null,
  "workaround": null,
  "resolution": "fixed",
  "resolutionDetails": "Feature was implemented as part of SDK enhancement to align with features repository specification.",
  "related": [],
  "keyQuote": "See `features` repo issue for more info",
  "number": 499,
  "repo": "temporalio-sdk-dotnet",
  "generatedAt": "2026-01-11T15:30:27.600Z"
}