{"assignees":[],"author":{"id":"MDQ6VXNlcjIyMzI1MjQ=","is_bot":false,"login":"alexshtin","name":"Alex Shtin"},"body":"## Expected Behavior\r\nNew workflow starts w/o errors.\r\n\r\n## Actual Behavior\r\nNew workflow fails to start, and `InvalidArgument` error with message indicating that search attribute is not found returned.\r\n","closedAt":"2022-08-30T23:27:10Z","comments":[],"createdAt":"2022-08-30T15:37:07Z","labels":[{"id":"MDU6TGFiZWwyMDE5ODE3MzQ2","name":"potential-bug","description":"","color":"66b9cc"}],"milestone":null,"number":3282,"reactionGroups":[],"state":"CLOSED","title":"Frontend handler retries may lead to InvalidArgument errors when starting new workflow","updatedAt":"2022-08-30T23:27:10Z","url":"https://github.com/temporalio/temporal/issues/3282"}
