{"assignees":[],"author":{"id":"MDQ6VXNlcjE2Nzg0Nw==","is_bot":false,"login":"Hades32","name":"Martin Rauscher"},"body":"Currently CRDB is working well with Temporal and the PostgreSQL v9.6 DB backend. But as e.g. https://github.com/temporalio/temporal/issues/4136 has shown, this was more accidental, although Temporal even provides a Docker Compose template that uses it.\r\n\r\nWe'd like to see CRDB becoming officially supported. The least I'd consider required for this is\r\n* SQL scripts either work for CRDB too or alternative scripts are provided\r\n* at least a subset of tests are run against CRDB in CI","closedAt":null,"comments":[{"id":"IC_kwDODNqesM5eDcWr","author":{"login":"navnit"},"authorAssociation":"NONE","body":"It would be great if we could get the official cockroachdb support. Please consider.","createdAt":"2023-06-06T05:57:33Z","includesCreatedEdit":false,"isMinimized":false,"minimizedReason":"","reactionGroups":[],"url":"https://github.com/temporalio/temporal/issues/4180#issuecomment-1577960875","viewerDidAuthor":false}],"createdAt":"2023-04-18T08:35:23Z","labels":[{"id":"MDU6TGFiZWwxNjIxMDMwNzg3","name":"enhancement","description":"New feature or request","color":"a2eeef"}],"milestone":null,"number":4180,"reactionGroups":[{"content":"THUMBS_UP","users":{"totalCount":13}},{"content":"HEART","users":{"totalCount":5}},{"content":"EYES","users":{"totalCount":4}}],"state":"OPEN","title":"Official CockroachDB (CRDB) support","updatedAt":"2023-06-06T05:57:33Z","url":"https://github.com/temporalio/temporal/issues/4180"}
