{"assignees":[],"author":{"id":"MDQ6VXNlcjIwNjM5Ng==","is_bot":false,"login":"cretz","name":"Chad Retz"},"body":"**Describe the solution you'd like**\n\nSee https://github.com/temporalio/features/issues/434","closedAt":"2025-03-25T18:11:41Z","comments":[{"id":"IC_kwDODN1w686kAlUX","author":{"login":"Quinn-With-Two-Ns"},"authorAssociation":"MEMBER","body":"@cretz this looks like a duplicate of https://github.com/temporalio/sdk-go/issues/1352","createdAt":"2025-03-25T15:15:47Z","includesCreatedEdit":false,"isMinimized":false,"minimizedReason":"","reactionGroups":[],"url":"https://github.com/temporalio/sdk-go/issues/1884#issuecomment-2751616279","viewerDidAuthor":false},{"id":"IC_kwDODN1w686kCkSm","author":{"login":"cretz"},"authorAssociation":"MEMBER","body":"Thanks! I'll close this as a duplicate and update that issue and the features issue to reference each other.","createdAt":"2025-03-25T18:11:41Z","includesCreatedEdit":false,"isMinimized":false,"minimizedReason":"","reactionGroups":[],"url":"https://github.com/temporalio/sdk-go/issues/1884#issuecomment-2752136358","viewerDidAuthor":false}],"createdAt":"2025-03-25T15:02:18Z","labels":[{"id":"MDU6TGFiZWwxNjIyNzA3NDky","name":"enhancement","description":"New feature or request","color":"a2eeef"}],"milestone":null,"number":1884,"reactionGroups":[],"state":"CLOSED","title":"Serialization context for codecs and converters","updatedAt":"2025-03-25T18:11:42Z","url":"https://github.com/temporalio/sdk-go/issues/1884"}
