{"assignees":[],"author":{"id":"MDQ6VXNlcjU5NDIyMjk=","is_bot":false,"login":"719media","name":""},"body":"**Is your feature request related to a problem? Please describe.**\nthe current datadog implementation is using an old version 1.58.1, and current datadog go sdk version is 2.5.0","closedAt":null,"comments":[{"id":"IC_kwDODN1w687gP3G8","author":{"login":"719media"},"authorAssociation":"NONE","body":"https://github.com/temporalio/sdk-go/pull/2155","createdAt":"2026-01-16T23:59:16Z","includesCreatedEdit":false,"isMinimized":false,"minimizedReason":"","reactionGroups":[],"url":"https://github.com/temporalio/sdk-go/issues/2154#issuecomment-3762254268","viewerDidAuthor":false}],"createdAt":"2026-01-16T23:20:24Z","labels":[{"id":"MDU6TGFiZWwxNjIyNzA3NDky","name":"enhancement","description":"New feature or request","color":"a2eeef"}],"milestone":null,"number":2154,"reactionGroups":[],"state":"OPEN","title":"Update datadog go integration to v2","updatedAt":"2026-01-16T23:59:16Z","url":"https://github.com/temporalio/sdk-go/issues/2154"}
