{"assignees":[],"author":{"id":"MDQ6VXNlcjUxNzY4Mw==","is_bot":false,"login":"Sushisource","name":"Spencer Judge"},"body":"The CPU/mem usage metrics that are present in Core/Java are absent here. https://docs.temporal.io/references/sdk-metrics#resource_slots_cpu_usage for reference.\n\nAdd them (and possibly also the pid value metrics, though those are less obviously useful and could be skipped).","closedAt":"2025-12-17T02:21:33Z","comments":[],"createdAt":"2025-10-23T22:52:41Z","labels":[{"id":"MDU6TGFiZWwxNjIyNzA3NDky","name":"enhancement","description":"New feature or request","color":"a2eeef"}],"milestone":null,"number":2089,"reactionGroups":[],"state":"CLOSED","title":"Add resource tuner metrics","updatedAt":"2025-12-17T02:21:33Z","url":"https://github.com/temporalio/sdk-go/issues/2089"}
