{"assignees":[],"author":{"id":"MDQ6VXNlcjk1NjM=","is_bot":false,"login":"robholland","name":"Rob Holland"},"body":"**Is your feature request related to a problem? Please describe.**\r\nFor testing we need UpdateWorkflowByID as the update equivalent of SignalWorkflowByID. This is needed to, for example, send an update to a child workflow of the workflow under test.\r\n\r\n**Describe alternatives you've considered**\r\nI can write a workflow in the test environment that sends the updates, but that is clumsy and complicates the tests.\r\n","closedAt":"2023-10-12T20:55:40Z","comments":[],"createdAt":"2023-10-11T09:40:06Z","labels":[{"id":"MDU6TGFiZWwxNjIyNzA3NDky","name":"enhancement","description":"New feature or request","color":"a2eeef"}],"milestone":null,"number":1263,"reactionGroups":[],"state":"CLOSED","title":"Add TestWorkflowEnvironment#UpdateWorkflowByID","updatedAt":"2023-10-12T20:55:40Z","url":"https://github.com/temporalio/sdk-go/issues/1263"}
