{"assignees":[],"author":{"id":"MDQ6VXNlcjUyMzA0","is_bot":false,"login":"bergundy","name":"Roey Berman"},"body":"https://github.com/temporalio/sdk-typescript/pull/468 changed the behavior of `WorkflowHandle` methods to use `run_id` only when a handle is created with one (`getHandle` in TS).\r\n\r\nHandles created with `start` should follow runs by default and use `first_execution_run_id` for safety (don't operate on runs that aren't part of the same execution chain).\r\nHandles created with `signal_with_start` should not use `run_id` but cannot yet guarantee safety, a server change is required for that.\r\n\r\n`getHandle` should accept a `first_execution_run_id` for safety.\r\n\r\nNOTE: `signal`, `query` and `describe` methods are unsafe at the time of this writing and require a server + API change.","closedAt":null,"comments":[{"id":"IC_kwDOGflYbs5oiU-g","author":{"login":"josh-berry"},"authorAssociation":"NONE","body":"@bergundy Should this be a TypeScript issue? Not sure why this is in `features`.","createdAt":"2023-10-09T20:51:25Z","includesCreatedEdit":false,"isMinimized":false,"minimizedReason":"","reactionGroups":[],"url":"https://github.com/temporalio/features/issues/22#issuecomment-1753829280","viewerDidAuthor":false},{"id":"IC_kwDOGflYbs5pn3JF","author":{"login":"bergundy"},"authorAssociation":"MEMBER","body":"This issue is to test and document the behavior across sdks","createdAt":"2023-10-20T04:23:06Z","includesCreatedEdit":false,"isMinimized":false,"minimizedReason":"","reactionGroups":[],"url":"https://github.com/temporalio/features/issues/22#issuecomment-1772057157","viewerDidAuthor":false}],"createdAt":"2022-02-23T00:11:07Z","labels":[{"id":"LA_kwDOGflYbs7XtLc6","name":"enhancement","description":"New feature or request","color":"a2eeef"}],"milestone":null,"number":22,"reactionGroups":[],"state":"OPEN","title":"[Feature Request] Spec for expected client behavior when using handle or stub methods","updatedAt":"2024-07-13T01:08:33Z","url":"https://github.com/temporalio/features/issues/22"}
