{"assignees":[],"author":{"id":"MDQ6VXNlcjIwNjM5Ng==","is_bot":false,"login":"cretz","name":"Chad Retz"},"body":"### Describe the solution you'd like\r\n\r\nNeed `--version latest` support for all SDKs. This should use language-dependent ways to use the latest tag. May also be worth updating CI to use this.","closedAt":null,"comments":[],"createdAt":"2022-11-18T13:25:22Z","labels":[{"id":"LA_kwDOGflYbs7XtLc6","name":"enhancement","description":"New feature or request","color":"a2eeef"}],"milestone":null,"number":166,"reactionGroups":[],"state":"OPEN","title":"[Feature Request] Support --version latest","updatedAt":"2024-07-13T01:07:34Z","url":"https://github.com/temporalio/features/issues/166"}
