{"assignees":[{"id":"MDQ6VXNlcjUxNzY4Mw==","login":"Sushisource","name":"Spencer Judge","databaseId":0}],"author":{"id":"MDQ6VXNlcjUyMzA0","is_bot":false,"login":"bergundy","name":"Roey Berman"},"body":"Occasionally, there's a need to modify SDK behavior in a history-incompatible manner.\r\nFor user logic, we have the marker based `getVersion` and `patched` APIs.\r\nWe do not have a standard mechanism for doing this in our SDKs apart from TypeScript where we use the `patched` API.\r\nIdeally there would be a way to encode this internal SDK version without creating new history events.\r\n\r\nA possible approach for solving this would be to add fields to the WorkflowTaskCompleted event and CompleteWorkflowTaskRequest proto messages.\r\n","closedAt":"2023-01-05T19:19:42Z","comments":[{"id":"IC_kwDOGflYbs5R0LHB","author":{"login":"bergundy"},"authorAssociation":"MEMBER","body":"Closing in favor of the more detailed #200 ","createdAt":"2023-01-05T19:19:42Z","includesCreatedEdit":false,"isMinimized":false,"minimizedReason":"","reactionGroups":[],"url":"https://github.com/temporalio/features/issues/197#issuecomment-1372631489","viewerDidAuthor":false}],"createdAt":"2023-01-04T23:24:08Z","labels":[{"id":"LA_kwDOGflYbs7XtLc6","name":"enhancement","description":"New feature or request","color":"a2eeef"}],"milestone":null,"number":197,"reactionGroups":[],"state":"CLOSED","title":"[Feature Request] Standard mechanism for versioning SDK logic","updatedAt":"2023-01-05T19:19:42Z","url":"https://github.com/temporalio/features/issues/197"}
