{
  "summary": "User asks how to test child workflows in the PHP SDK, referencing the sample ParentWorkflow implementation. The question was redirected to Slack for community support.",
  "category": "question",
  "subcategory": "testing",
  "apis": [],
  "components": [
    "test-framework",
    "workflow-execution"
  ],
  "concepts": [
    "child-workflow",
    "testing",
    "workflow-composition"
  ],
  "severity": "low",
  "userImpact": "Users need guidance on testing patterns for child workflows in PHP applications.",
  "rootCause": null,
  "proposedFix": null,
  "workaround": null,
  "resolution": "invalid",
  "resolutionDetails": "Issue redirected to Slack community support channel rather than being addressed as a product issue.",
  "related": [],
  "keyQuote": "Feel free to raise your question in the Slack, our team would be happy to help you",
  "number": 236,
  "repo": "temporalio-sdk-php",
  "generatedAt": "2026-01-11T20:24:36.543Z"
}