{"assignees":[],"author":{"id":"MDQ6VXNlcjIwNjM5Ng==","is_bot":false,"login":"cretz","name":"Chad Retz"},"body":"### Is your feature request related to a problem? Please describe.\r\n\r\nRight now this is buried in the default constructor, but people may want this list for other reasons\r\n\r\n### Describe the solution you'd like\r\n\r\nMake the list available","closedAt":"2022-11-07T14:17:04Z","comments":[{"id":"IC_kwDOGusT1c5MGY3J","author":{"login":"cretz"},"authorAssociation":"MEMBER","body":"Also, just make creating a data converter (and payload converter) with a different encoding payload converter prepended to the default list easier. Maybe something like `temporalio.converter.default().with_encoding_payload_converter(...`.","createdAt":"2022-10-12T21:12:54Z","includesCreatedEdit":false,"isMinimized":false,"minimizedReason":"","reactionGroups":[],"url":"https://github.com/temporalio/sdk-python/issues/139#issuecomment-1276743113","viewerDidAuthor":false}],"createdAt":"2022-09-19T19:28:31Z","labels":[{"id":"LA_kwDOGusT1c7gQgHN","name":"enhancement","description":"New feature or request","color":"a2eeef"}],"milestone":null,"number":139,"reactionGroups":[],"state":"CLOSED","title":"Expose default sequence of payload converters for custom converter creators","updatedAt":"2022-11-07T14:17:04Z","url":"https://github.com/temporalio/sdk-python/issues/139"}
