{"assignees":[],"author":{"id":"MDQ6VXNlcjIwNjM5Ng==","is_bot":false,"login":"cretz","name":"Chad Retz"},"body":"### Describe the bug\r\n\r\nhttps://github.com/temporalio/sdk-python/blob/24fea4cc31eded8b32e3619490b68554c0b52376/temporalio/testing/_workflow.py#L565 should be `config[\"interceptors\"] = config_interceptors`.","closedAt":"2023-08-07T22:28:09Z","comments":[],"createdAt":"2023-08-07T13:16:25Z","labels":[{"id":"LA_kwDOGusT1c7gQgHK","name":"bug","description":"Something isn't working","color":"d73a4a"}],"milestone":null,"number":363,"reactionGroups":[],"state":"CLOSED","title":"[Bug] Testing environment overrides set interceptors","updatedAt":"2023-08-07T22:28:09Z","url":"https://github.com/temporalio/sdk-python/issues/363"}
