{"assignees":[],"author":{"id":"MDQ6VXNlcjUyMjA1","is_bot":false,"login":"dandavison","name":"Dan Davison"},"body":"Workflow cancellation results in `WorkflowFailureError(\"workflow execution failed\")`. It would make sense for that to be `WorkflowFailureError(\"workflow execution cancelled\")`.","closedAt":"2024-07-17T15:40:24Z","comments":[{"id":"IC_kwDOGusT1c6FImS5","author":{"login":"dandavison"},"authorAssociation":"MEMBER","body":"Actually, this suggestion isn't appropriate: it makes sense that the outer message has a natural language string matching its class name; the cancellation exception is contained within the outer exception as the `__cause__` (exposed as `.cause`)","createdAt":"2024-07-17T15:40:24Z","includesCreatedEdit":false,"isMinimized":false,"minimizedReason":"","reactionGroups":[],"url":"https://github.com/temporalio/sdk-python/issues/583#issuecomment-2233623737","viewerDidAuthor":false}],"createdAt":"2024-07-17T15:13:27Z","labels":[{"id":"LA_kwDOGusT1c7gQgHN","name":"enhancement","description":"New feature or request","color":"a2eeef"}],"milestone":null,"number":583,"reactionGroups":[],"state":"CLOSED","title":"Tweak error message on workflow cancellation","updatedAt":"2024-07-17T15:40:24Z","url":"https://github.com/temporalio/sdk-python/issues/583"}
