{"assignees":[],"author":{"id":"MDQ6VXNlcjY0MTIxNjk=","is_bot":false,"login":"mjameswh","name":"James Watkins-Harvey"},"body":"### Describe the bug\r\n\r\nSee [here](https://typescript.temporal.io/api/namespaces/worker#defaultworflowinterceptormodules).","closedAt":"2023-08-16T22:47:27Z","comments":[{"id":"IC_kwDOEujx185kN5dJ","author":{"login":"mjameswh"},"authorAssociation":"MEMBER","body":"Fixed by #1204.","createdAt":"2023-08-16T22:47:27Z","includesCreatedEdit":false,"isMinimized":false,"minimizedReason":"","reactionGroups":[],"url":"https://github.com/temporalio/sdk-typescript/issues/1196#issuecomment-1681364809","viewerDidAuthor":false}],"createdAt":"2023-08-09T23:38:30Z","labels":[{"id":"MDU6TGFiZWwyNTQ1Mzg0MDA2","name":"bug","description":"Something isn't working","color":"d73a4a"}],"milestone":null,"number":1196,"reactionGroups":[],"state":"CLOSED","title":"[Bug] Typo in `defaultWorflowInterceptorModules` API","updatedAt":"2023-08-16T22:47:27Z","url":"https://github.com/temporalio/sdk-typescript/issues/1196"}
