{"assignees":[],"author":{"id":"MDQ6VXNlcjM4MTcwNTE1","is_bot":false,"login":"Thexumaker","name":"David Xu"},"body":"### What are you really trying to do?\r\nI'm trying to query for some workflow data via the temporal client list method.\r\n\r\n### Describe the bug\r\n\r\nI'm calling temporalClient.list({pageSize: 1, query: 'randomQuery'}) but it seems to just returns thousands of results\r\n\r\nThe result should've returned just 1 item but I get back a thousand results.\r\n\r\n### Minimal Reproduction\r\n\r\n```\r\nconst iterable = temporalClient.list({\r\n      pageSize: 1,\r\n      query: `userId = '123'`,\r\n    });\r\n\r\n    const results = [];\r\n    for await (const item of iterable) {\r\n      results.push(item);\r\n    }\r\n\r\n    logger.info(`length of results: ${results.length}` );\r\n ```\r\n    \r\n    It should return 1 result based on the docs, but I also couldn't find too much documentation for this\r\n\r\n### Environment/Versions\r\n\r\n<!-- Please complete the following information where relevant. -->\r\n\r\n- OS and processor: M1 mac\r\n- Temporal Version: 1.19 SDK\r\n- Are you using Docker or Kubernetes or building Temporal from source?\r\nDocker\r\n\r\n### Additional context\r\n\r\n<!-- Add any other context about the problem here. -->\r\n\r\nI'm not too concerned by this issue but reading the docs(https://docs.temporal.io/visibility#efficient-api-usage) I'm not really able to test pagination which will become a blocker in the future","closedAt":"2024-03-26T21:34:48Z","comments":[{"id":"IC_kwDOEujx186YEdbJ","author":{"login":"jpalof"},"authorAssociation":"NONE","body":"@Thexumaker , I am having a similar problem (https://community.temporal.io/t/problem-limiting-results-of-workflowclient-list-pagesize-1/15725).  I noticed that you marked this bug as `completed`.  I don't see a fix associated with this bug.  Did you discover a mis-conception on your usage or a workaround that resulted you in closing this bug?\r\n\r\nThanks","createdAt":"2024-12-18T13:20:07Z","includesCreatedEdit":false,"isMinimized":false,"minimizedReason":"","reactionGroups":[],"url":"https://github.com/temporalio/sdk-typescript/issues/1382#issuecomment-2551305929","viewerDidAuthor":false}],"createdAt":"2024-03-26T21:16:33Z","labels":[{"id":"MDU6TGFiZWwyNTQ1Mzg0MDA2","name":"bug","description":"Something isn't working","color":"d73a4a"}],"milestone":null,"number":1382,"reactionGroups":[],"state":"CLOSED","title":"[Bug] Page size filter in @temporalio/client list method doesn't seem to be working properly","updatedAt":"2024-12-18T13:20:10Z","url":"https://github.com/temporalio/sdk-typescript/issues/1382"}
