{"assignees":[{"id":"MDQ6VXNlcjUyMzA0","login":"bergundy","name":"Roey Berman","databaseId":0}],"author":{"id":"MDQ6VXNlcjI4Njc5","is_bot":false,"login":"joebowbeer","name":"Joe Bowbeer"},"body":"### Describe the bug\r\n\r\nWorker.create with workDir and activities undefined does not work.\r\n\r\n_Originally posted by @joebowbeer in https://github.com/temporalio/temporal-pendulum/pull/2#discussion_r702903504_\r\n\r\n### To Reproduce\r\n\r\nhttps://github.com/temporalio/temporal-pendulum/blob/main/position-node/src/worker.ts#L5-L7\r\n\r\n```suggestion\r\n    workDir: __dirname,\r\n    activities: undefined,\r\n```\r\n\r\nI tried this^ simpler form, but it failed because of activities MODULE_NOT_FOUND: \r\n\r\n```\r\nError: Cannot find module '[...]/temporal-pendulum/position-node/src/activities'\r\n```\r\n\r\n### Versions\r\n\r\n- Temporal Node SDK 0.4.1","closedAt":"2021-09-15T05:54:18Z","comments":[],"createdAt":"2021-09-07T20:01:17Z","labels":[{"id":"MDU6TGFiZWwyNTQ1Mzg0MDA2","name":"bug","description":"Something isn't working","color":"d73a4a"}],"milestone":{"number":2,"title":"beta","description":"","dueOn":null},"number":227,"reactionGroups":[],"state":"CLOSED","title":"[Bug] Worker.create fails with activities undefined","updatedAt":"2021-09-15T05:54:18Z","url":"https://github.com/temporalio/sdk-typescript/issues/227"}
