{
  "summary": "Feature request to implement typed search attributes for the TypeScript SDK, as defined in the cross-SDK proposal. This would provide type-safe access to search attributes in workflows and activities.",
  "category": "feature",
  "subcategory": "search-attributes",
  "apis": [],
  "components": [
    "search-attributes",
    "type-system",
    "workflow-api"
  ],
  "concepts": [
    "type-safety",
    "search-attributes",
    "workflow-queries",
    "data-validation",
    "api-ergonomics"
  ],
  "severity": "medium",
  "userImpact": "Enables developers to define and use search attributes with full type safety, reducing runtime errors and improving developer experience.",
  "rootCause": null,
  "proposedFix": "Implement typed search attributes following the SDK proposal specification",
  "workaround": null,
  "resolution": "fixed",
  "resolutionDetails": "Feature was implemented and completed",
  "related": [],
  "keyQuote": "Implementation of typed search attributes",
  "number": 1232,
  "repo": "temporalio-sdk-typescript",
  "generatedAt": "2026-01-12T05:39:03.256Z"
}