{
  "summary": "Feature request to rename the 'codec' configuration option to 'codecs' in the TypeScript SDK for consistency and clarity.",
  "category": "feature",
  "subcategory": "codec-naming",
  "apis": [],
  "components": [
    "codec-system",
    "configuration"
  ],
  "concepts": [
    "naming-convention",
    "api-consistency",
    "configuration",
    "payload-encoding"
  ],
  "severity": "low",
  "userImpact": "Users would benefit from more intuitive naming that better reflects that multiple codecs can be used.",
  "rootCause": null,
  "proposedFix": "Rename the 'codec' property to 'codecs' in the SDK configuration.",
  "workaround": null,
  "resolution": "fixed",
  "resolutionDetails": "The codec configuration was renamed to codecs to better represent multiple codec support.",
  "related": [],
  "keyQuote": null,
  "number": 595,
  "repo": "temporalio-sdk-typescript",
  "generatedAt": "2026-01-11T23:03:26.724Z"
}