{
  "summary": "Research and evaluate the Temporal Core API to determine compatibility and integration strategy for the Ruby SDK.",
  "category": "other",
  "subcategory": "core-api-research",
  "apis": [],
  "components": [
    "core-api",
    "sdk-integration"
  ],
  "concepts": [
    "api-compatibility",
    "sdk-design",
    "integration-strategy",
    "core-evaluation",
    "research"
  ],
  "severity": "medium",
  "userImpact": "Understanding the Core API is essential for proper Ruby SDK implementation and ensuring alignment with other language SDKs.",
  "rootCause": null,
  "proposedFix": null,
  "workaround": null,
  "resolution": "fixed",
  "resolutionDetails": "Research task completed and Core API evaluated as part of Ruby SDK development",
  "related": [],
  "keyQuote": null,
  "number": 17,
  "repo": "temporalio-sdk-ruby",
  "generatedAt": "2026-01-11T21:38:35.428Z"
}