{
  "summary": "Feature request to enable setting API key and RPC metadata on the live Temporal Ruby client, allowing users to configure authentication and metadata for RPC calls.",
  "category": "feature",
  "subcategory": "client-configuration",
  "apis": [
    "Client"
  ],
  "components": [
    "client",
    "rpc",
    "authentication"
  ],
  "concepts": [
    "api-key",
    "rpc-metadata",
    "authentication",
    "client-configuration",
    "security"
  ],
  "severity": "medium",
  "userImpact": "Users cannot dynamically configure API keys and RPC metadata on the Ruby client, limiting authentication and request customization options.",
  "rootCause": null,
  "proposedFix": null,
  "workaround": null,
  "resolution": "fixed",
  "resolutionDetails": "The issue was closed, indicating the feature was implemented in the Ruby SDK",
  "related": [],
  "keyQuote": "Need to be able to set the API key and RPC metadata on the live client",
  "number": 164,
  "repo": "temporalio-sdk-ruby",
  "generatedAt": "2026-01-11T21:43:52.165Z"
}