{"assignees":[],"author":{"id":"MDQ6VXNlcjExOTQyMg==","is_bot":false,"login":"tsurdilo","name":"Tihomir Surdilovic"},"body":"Feature request is to please add ability to query via ExternalWorkflowStub. Currently signal is only possible.","closedAt":"2023-01-05T07:17:28Z","comments":[{"id":"IC_kwDODN12PM5RxPbX","author":{"login":"Spikhalskiy"},"authorAssociation":"CONTRIBUTOR","body":"This is not an SDK issue. ExternalWorkflowStub has an underlying implementation in state machines and produces commands. There is no command and no underlying workflow history baked implementation for query currently.\r\nSo, this needs a new command and Server support first.\r\nWorkaround: use an activity to query an external workflow.","createdAt":"2023-01-05T07:17:28Z","includesCreatedEdit":false,"isMinimized":false,"minimizedReason":"","reactionGroups":[],"url":"https://github.com/temporalio/sdk-java/issues/1584#issuecomment-1371862743","viewerDidAuthor":false},{"id":"IC_kwDODN12PM6RWzLW","author":{"login":"rocketraman"},"authorAssociation":"NONE","body":"Do we have a tracking issue for the new command and server support for this? I also can't do `@Update` from a parent workflow, and it is quite an annoyance to have to delegate the call to an activity.","createdAt":"2024-10-25T19:46:43Z","includesCreatedEdit":false,"isMinimized":false,"minimizedReason":"","reactionGroups":[],"url":"https://github.com/temporalio/sdk-java/issues/1584#issuecomment-2438673110","viewerDidAuthor":false}],"createdAt":"2023-01-05T05:22:44Z","labels":[{"id":"LA_kwDODN12PM7NRayD","name":"wontfix","description":"This will not be worked on","color":"BFD4F2"}],"milestone":null,"number":1584,"reactionGroups":[],"state":"CLOSED","title":"ExternalWorkflowStub query","updatedAt":"2024-10-25T19:46:44Z","url":"https://github.com/temporalio/sdk-java/issues/1584"}
