{"assignees":[],"author":{"id":"MDQ6VXNlcjE0NjM2MjI=","is_bot":false,"login":"mfateev","name":"Maxim Fateev"},"body":"## Expected Behavior\r\nShould support continue as new with methods without arguments.\r\n\r\n    @Override\r\n    public void run() {\r\n        .....\r\n        continueAsNewWorkflow.run();\r\n    }\r\n\r\n\r\n## Actual Behavior\r\n\"java.lang.NullPointerException\\\\n\\\\tat io.temporal.proto.decision.ContinueAsNewWorkflowExecutionDecisionAttributes$Builder.setInput(ContinueAsNewWorkflowExecutionDecisionAttributes.java:1494)\\\\n\\\\tat io.temporal.internal.replay.DecisionsHelper.continueAsNewWorkflowExecution(DecisionsHelper.java:442)\r\n\r\n## Steps to Reproduce the Problem\r\nCall continue as new on a workflow with @WorkflowMethod without arguments.\r\n\r\n## Specifications\r\n0.23.1 release of Java SDK\r\n\r\n## Solution\r\n","closedAt":"2020-06-22T04:52:25Z","comments":[],"createdAt":"2020-06-04T22:18:52Z","labels":[{"id":"MDU6TGFiZWwxNjIyNzE5ODQx","name":"bug","description":"Something isn't working","color":"d73a4a"}],"milestone":null,"number":98,"reactionGroups":[],"state":"CLOSED","title":"NPE on null input when calling continue as new","updatedAt":"2020-06-22T04:52:25Z","url":"https://github.com/temporalio/sdk-java/issues/98"}
